erichek/__init__.py
erichek/__main__.py
erichek/eric_body.py
erichek/eric_config.py
erichek/eric_encoding.py
erichek/eric_head.py
erichek/eric_regex.py
erichek/eric_summary.py
erichek-0.4.0.dist-info/LICENSE.md
erichek-0.4.0.dist-info/METADATA
erichek-0.4.0.dist-info/WHEEL
erichek-0.4.0.dist-info/entry_points.txt
erichek-0.4.0.dist-info/top_level.txt
erichek-0.4.0.dist-info/RECORD
